odoo/addons/calendar_event_link_project_task/README.rst
odoo/addons/calendar_event_link_project_task/__init__.py
odoo/addons/calendar_event_link_project_task/__manifest__.py
odoo/addons/calendar_event_link_project_task/i18n/calendar_event_link_project_task.pot
odoo/addons/calendar_event_link_project_task/models/__init__.py
odoo/addons/calendar_event_link_project_task/models/project_task.py
odoo/addons/calendar_event_link_project_task/readme/CONTRIBUTORS.rst
odoo/addons/calendar_event_link_project_task/readme/DESCRIPTION.rst
odoo/addons/calendar_event_link_project_task/static/description/icon.png
odoo/addons/calendar_event_link_project_task/static/description/index.html
odoo/addons/calendar_event_link_project_task/tests/__init__.py
odoo/addons/calendar_event_link_project_task/tests/test_calendar_event_link.py
odoo/addons/calendar_event_link_project_task/views/project_task.xml
odoo12_addon_calendar_event_link_project_task-12.0.1.0.0.99.dev5.dist-info/METADATA
odoo12_addon_calendar_event_link_project_task-12.0.1.0.0.99.dev5.dist-info/WHEEL
odoo12_addon_calendar_event_link_project_task-12.0.1.0.0.99.dev5.dist-info/top_level.txt
odoo12_addon_calendar_event_link_project_task-12.0.1.0.0.99.dev5.dist-info/RECORD
